odoo8_addon_hr_job_categories-8.0.1.0.0.99.dev11-py2.7-nspkg.pth
odoo8_addon_hr_job_categories-8.0.1.0.0.99.dev11.dist-info/DESCRIPTION.rst
odoo8_addon_hr_job_categories-8.0.1.0.0.99.dev11.dist-info/METADATA
odoo8_addon_hr_job_categories-8.0.1.0.0.99.dev11.dist-info/RECORD
odoo8_addon_hr_job_categories-8.0.1.0.0.99.dev11.dist-info/WHEEL
odoo8_addon_hr_job_categories-8.0.1.0.0.99.dev11.dist-info/metadata.json
odoo8_addon_hr_job_categories-8.0.1.0.0.99.dev11.dist-info/namespace_packages.txt
odoo8_addon_hr_job_categories-8.0.1.0.0.99.dev11.dist-info/top_level.txt
odoo_addons/hr_job_categories/README.rst
odoo_addons/hr_job_categories/__init__.py
odoo_addons/hr_job_categories/__openerp__.py
odoo_addons/hr_job_categories/i18n/ca.po
odoo_addons/hr_job_categories/i18n/de.po
odoo_addons/hr_job_categories/i18n/es.po
odoo_addons/hr_job_categories/i18n/fi.po
odoo_addons/hr_job_categories/i18n/fr.po
odoo_addons/hr_job_categories/i18n/hr_job_categories.pot
odoo_addons/hr_job_categories/i18n/it.po
odoo_addons/hr_job_categories/i18n/pt_BR.po
odoo_addons/hr_job_categories/i18n/ro.po
odoo_addons/hr_job_categories/i18n/sl.po
odoo_addons/hr_job_categories/i18n/zh_CN.po
odoo_addons/hr_job_categories/models/__init__.py
odoo_addons/hr_job_categories/models/hr.py
odoo_addons/hr_job_categories/static/description/icon.png
odoo_addons/hr_job_categories/tests/__init__.py
odoo_addons/hr_job_categories/tests/test_hr_job_categories.py
odoo_addons/hr_job_categories/views/hr_view.xml
